{
  "state-hist-summary": {
    '_all': {'enabled': "false" },
    "_parent": {
      "type": "run"
    },
    "properties": {
      "hmini": {
        "properties": {
          "entries": {
            "type" : "nested",
            "properties": {
              "key": {
                "type": "short"
              },
              "count": {
                "type": "integer"
              }
            }
          },
          "total": {
            "type": "integer"
          }
        }
      },
      "hmicro": {
        "properties": {
          "entries": {
            "type" : "nested",
            "properties": {
              "key": {
                "type": "short"
              },
              "count": {
                "type": "integer"
              }
            }
          },
          "total": {
            "type": "integer"
          }
        }
      },
      "hmacro": {
        "properties": {
          "entries": {
            "type" : "nested",
            "properties": {
              "key": {
                "type": "short"
              },
              "count": {
                "type": "integer"
              }
            }
          },
          "total": {
            "type": "integer"
          }
        }
      },
      "hinput": {
        "properties": {
          "entries": {
            "type" : "nested",
            "properties": {
              "key": {
                "type": "short"
              },
              "count": {
                "type": "integer"
              }
            }
          },
          "total": {
            "type": "integer"
          }
        }
      },
      "date":{
        "type":"date"
      },
      "fm_date":{
        "type":"date"
      },
      "cpuslotsmax":{
        "type":"short"
      },
      "cpuslots":{
        "type":"short"
      }
    }
  }
}
